pydargs/__init__.py
pydargs/_version.py
pydargs/py.typed
pydargs/utils.py
pydargs-0.11.0.dist-info/LICENSE
pydargs-0.11.0.dist-info/METADATA
pydargs-0.11.0.dist-info/WHEEL
pydargs-0.11.0.dist-info/top_level.txt
pydargs-0.11.0.dist-info/RECORD
