Metadata-Version: 2.1
Name: pydargs
Version: 0.11.0
Summary: Easily configure a CLI application using a (Pydantic) dataclass.
Author-email: Anton Steenvoorden <Anton.Steenvoorden@ah.nl>, Guus Verstegen <gjaverstegen@gmail.com>, Rogier van der Geer <rogier@vander-geer.nl>
License: BSD
Project-URL: Repository, https://github.com/rogiervandergeer/pydargs
Keywords: cli,dataclass
Classifier: Environment :: Console
Classifier: Intended Audience :: Developers
Classifier: License :: OSI Approved :: BSD License
Classifier: Operating System :: OS Independent
Classifier: Programming Language :: Python :: 3
Classifier: Typing :: Typed
Requires-Python: >=3.9
License-File: LICENSE
Provides-Extra: dev
Requires-Dist: mypy ==1.6.1 ; extra == 'dev'
Requires-Dist: pre-commit ==3.5.0 ; extra == 'dev'
Requires-Dist: ruff ==0.1.5 ; extra == 'dev'
Requires-Dist: pytest ==7.4.3 ; extra == 'dev'
Requires-Dist: pydargs[yaml] ; extra == 'dev'
Provides-Extra: pydantic
Requires-Dist: pydantic >=2.0 ; extra == 'pydantic'
Provides-Extra: yaml
Requires-Dist: pyyaml >=5.0 ; extra == 'yaml'
